README.rst
chanterelle.py
setup.py
chanterelle.egg-info/PKG-INFO
chanterelle.egg-info/SOURCES.txt
chanterelle.egg-info/dependency_links.txt
chanterelle.egg-info/entry_points.txt
chanterelle.egg-info/requires.txt
chanterelle.egg-info/top_level.txt