Metadata-Version: 1.1
Name: chanterelle
Version: 1.0.0
Summary: Utility for uploading static site files to an S3 bucket.
Home-page: https://github.com/unixispower/chanterelle
Author: Blaine Murphy
Author-email: myself@blaines.world
License: MIT
Platform: UNKNOWN
Classifier: Development Status :: 4 - Beta
Classifier: Environment :: Console
Classifier: Intended Audience :: Developers
Classifier: License :: OSI Approved :: MIT License
Classifier: Programming Language :: Python
Classifier: Programming Language :: Python :: 3 :: Only
Classifier: Topic :: Internet :: WWW/HTTP :: Site Management
